predictiveanalytics/NN.py
predictiveanalytics/__init__.py
predictiveanalytics/linear_regression.py
predictiveanalytics-0.0.5.dist-info/METADATA
predictiveanalytics-0.0.5.dist-info/RECORD
predictiveanalytics-0.0.5.dist-info/WHEEL
predictiveanalytics-0.0.5.dist-info/top_level.txt
