Metadata-Version: 2.1
Name: predictiveanalytics
Version: 0.0.5
Summary: Tools and Algorithms used for Predictive Analytics and Machine Learning
Home-page: http://github.com/bawdiest/predictiveanalytics
Author: bawdiest
Author-email: com@mikmak.cc
License: UNKNOWN
Platform: UNKNOWN
Classifier: Programming Language :: Python :: 2
Classifier: License :: OSI Approved :: MIT License
Classifier: Operating System :: OS Independent
